bb_unsucked/__init__.py
bb_unsucked/__main__.py
bb_unsucked/ftp_fs.py
bb_unsucked/fuse_fs.py
bb_unsucked-0.0.14.dist-info/LICENSE
bb_unsucked-0.0.14.dist-info/METADATA
bb_unsucked-0.0.14.dist-info/WHEEL
bb_unsucked-0.0.14.dist-info/top_level.txt
bb_unsucked-0.0.14.dist-info/RECORD
