Metadata-Version: 2.1
Name: bb-unsucked
Version: 0.0.14
Summary: A solution to Blackboard misery for college students and professors
Home-page: https://git-community.cs.odu.edu/jmcateer/blackboard-unsucked
Author: Jeffrey McAteer
Author-email: jeffrey.p.mcateer@outlook.com
License: UNKNOWN
Platform: UNKNOWN
Classifier: Programming Language :: Python :: 3
Classifier: License :: OSI Approved :: GNU General Public License v2 (GPLv2)
Classifier: Operating System :: OS Independent
